{
"meta":{"test_sets":[],"test_metrics":[],"learn_metrics":[{"best_value":"Min","name":"MultiClass"}],"launch_mode":"Train","parameters":"","iteration_count":500,"learn_sets":["learn"],"name":"experiment"},
"iterations":[
{"learn":[1.06997012],"iteration":0,"passed_time":0.1041835292,"remaining_time":51.98758107},
{"learn":[1.044574502],"iteration":1,"passed_time":0.2406403869,"remaining_time":59.91945635},
{"learn":[1.019906369],"iteration":2,"passed_time":0.4293315387,"remaining_time":71.12592492},
{"learn":[0.9978152494],"iteration":3,"passed_time":0.6756710472,"remaining_time":83.78320985},
{"learn":[0.9774220837],"iteration":4,"passed_time":0.8504829464,"remaining_time":84.19781169},
{"learn":[0.9580509265],"iteration":5,"passed_time":1.030236767,"remaining_time":84.82282718},
{"learn":[0.9376775118],"iteration":6,"passed_time":1.293094392,"remaining_time":91.07079073},
{"learn":[0.9212954086],"iteration":7,"passed_time":1.522499283,"remaining_time":93.63370593},
{"learn":[0.904228154],"iteration":8,"passed_time":1.674032704,"remaining_time":91.32778416},
{"learn":[0.8899733074],"iteration":9,"passed_time":1.829896056,"remaining_time":89.66490675},
{"learn":[0.8755234682],"iteration":10,"passed_time":1.984369409,"remaining_time":88.21424008},
{"learn":[0.8617610324],"iteration":11,"passed_time":2.133593008,"remaining_time":86.76611568},
{"learn":[0.8496095581],"iteration":12,"passed_time":2.24702514,"remaining_time":84.17701872},
{"learn":[0.8363922789],"iteration":13,"passed_time":2.374977834,"remaining_time":82.44565908},
{"learn":[0.8235116378],"iteration":14,"passed_time":2.501590859,"remaining_time":80.8847711},
{"learn":[0.8109577622],"iteration":15,"passed_time":2.659849063,"remaining_time":80.46043416},
{"learn":[0.8000556132],"iteration":16,"passed_time":2.824669053,"remaining_time":80.25383251},
{"learn":[0.7898825447],"iteration":17,"passed_time":2.979357307,"remaining_time":79.78056788},
{"learn":[0.7781012297],"iteration":18,"passed_time":3.126533156,"remaining_time":79.15065516},
{"learn":[0.7693437629],"iteration":19,"passed_time":3.250825711,"remaining_time":78.01981707},
{"learn":[0.7595777413],"iteration":20,"passed_time":3.387152137,"remaining_time":77.25932732},
{"learn":[0.7498721926],"iteration":21,"passed_time":3.530458003,"remaining_time":76.70722388},
{"learn":[0.7405108651],"iteration":22,"passed_time":3.684341266,"remaining_time":76.41003408},
{"learn":[0.7328225442],"iteration":23,"passed_time":3.80493919,"remaining_time":75.46462726},
{"learn":[0.7251129221],"iteration":24,"passed_time":3.92168701,"remaining_time":74.51205318},
{"learn":[0.7181385247],"iteration":25,"passed_time":4.033390631,"remaining_time":73.5318138},
{"learn":[0.7105637219],"iteration":26,"passed_time":4.146427951,"remaining_time":72.63927485},
{"learn":[0.7032924162],"iteration":27,"passed_time":4.258766634,"remaining_time":71.79063755},
{"learn":[0.6960608494],"iteration":28,"passed_time":4.376885498,"remaining_time":71.08665757},
{"learn":[0.6884613068],"iteration":29,"passed_time":4.494433165,"remaining_time":70.41278625},
{"learn":[0.6806056355],"iteration":30,"passed_time":4.609348432,"remaining_time":69.73498111},
{"learn":[0.6741440182],"iteration":31,"passed_time":4.729398975,"remaining_time":69.16746001},
{"learn":[0.6680527989],"iteration":32,"passed_time":4.851106864,"remaining_time":68.65051228},
{"learn":[0.6589680829],"iteration":33,"passed_time":4.962286714,"remaining_time":68.0125179},
{"learn":[0.6515781866],"iteration":34,"passed_time":5.060473877,"remaining_time":67.23201008},
{"learn":[0.6463946102],"iteration":35,"passed_time":5.167683643,"remaining_time":66.60570028},
{"learn":[0.6396335625],"iteration":36,"passed_time":5.276297298,"remaining_time":66.02501754},
{"learn":[0.6319200037],"iteration":37,"passed_time":5.374768757,"remaining_time":65.34587278},
{"learn":[0.625677649],"iteration":38,"passed_time":5.490006622,"remaining_time":64.89469366},
{"learn":[0.6207664036],"iteration":39,"passed_time":5.606584427,"remaining_time":64.47572091},
{"learn":[0.6154269201],"iteration":40,"passed_time":5.706221311,"remaining_time":63.88184346},
{"learn":[0.6106525559],"iteration":41,"passed_time":5.834490387,"remaining_time":63.62372851},
{"learn":[0.6070759704],"iteration":42,"passed_time":5.963850308,"remaining_time":63.3832463},
{"learn":[0.6032189251],"iteration":43,"passed_time":6.098971187,"remaining_time":63.20751958},
{"learn":[0.5973397051],"iteration":44,"passed_time":6.237780836,"remaining_time":63.07089511},
{"learn":[0.592861099],"iteration":45,"passed_time":6.370058489,"remaining_time":62.86970769},
{"learn":[0.5872642525],"iteration":46,"passed_time":6.516319409,"remaining_time":62.8062275},
{"learn":[0.5830801083],"iteration":47,"passed_time":6.650937801,"remaining_time":62.62966429},
{"learn":[0.5776892121],"iteration":48,"passed_time":6.770796677,"remaining_time":62.31896533},
{"learn":[0.5724822524],"iteration":49,"passed_time":6.906310542,"remaining_time":62.15679488},
{"learn":[0.5687402591],"iteration":50,"passed_time":7.029401169,"remaining_time":61.88629656},
{"learn":[0.5650427025],"iteration":51,"passed_time":7.162462572,"remaining_time":61.70736985},
{"learn":[0.5595559131],"iteration":52,"passed_time":7.290540331,"remaining_time":61.48814203},
{"learn":[0.5557003871],"iteration":53,"passed_time":7.421998225,"remaining_time":61.30020756},
{"learn":[0.5509767888],"iteration":54,"passed_time":7.560157813,"remaining_time":61.16854957},
{"learn":[0.5470291159],"iteration":55,"passed_time":7.702712564,"remaining_time":61.07150676},
{"learn":[0.5425841519],"iteration":56,"passed_time":7.867980215,"remaining_time":61.14939009},
{"learn":[0.5387224697],"iteration":57,"passed_time":8.067752079,"remaining_time":61.48183481},
{"learn":[0.534362776],"iteration":58,"passed_time":8.252626738,"remaining_time":61.68488799},
{"learn":[0.5298056773],"iteration":59,"passed_time":8.422105204,"remaining_time":61.76210483},
{"learn":[0.5268902787],"iteration":60,"passed_time":8.551525393,"remaining_time":61.54294504},
{"learn":[0.5234340622],"iteration":61,"passed_time":8.701672634,"remaining_time":61.47310667},
{"learn":[0.5197230191],"iteration":62,"passed_time":8.826723538,"remaining_time":61.22663787},
{"learn":[0.5157293051],"iteration":63,"passed_time":8.955450721,"remaining_time":61.00900804},
{"learn":[0.5122573013],"iteration":64,"passed_time":9.064665533,"remaining_time":60.66353088},
{"learn":[0.5092703719],"iteration":65,"passed_time":9.187935214,"remaining_time":60.41763459},
{"learn":[0.505622567],"iteration":66,"passed_time":9.350533747,"remaining_time":60.42956884},
{"learn":[0.5022482029],"iteration":67,"passed_time":9.508475477,"remaining_time":60.40678538},
{"learn":[0.4988450983],"iteration":68,"passed_time":9.679081425,"remaining_time":60.45918977},
{"learn":[0.4950820861],"iteration":69,"passed_time":9.832809348,"remaining_time":60.40154314},
{"learn":[0.4918809463],"iteration":70,"passed_time":9.984918141,"remaining_time":60.33140679},
{"learn":[0.4873096285],"iteration":71,"passed_time":10.12229985,"remaining_time":60.17144913},
{"learn":[0.4843688632],"iteration":72,"passed_time":10.27922964,"remaining_time":60.12645284},
{"learn":[0.4813907827],"iteration":73,"passed_time":10.41676517,"remaining_time":59.96678329},
{"learn":[0.4788604952],"iteration":74,"passed_time":10.55512306,"remaining_time":59.81236402},
{"learn":[0.4759530943],"iteration":75,"passed_time":10.71150876,"remaining_time":59.75894363},
{"learn":[0.472440565],"iteration":76,"passed_time":10.92636146,"remaining_time":60.02403761},
{"learn":[0.4705953265],"iteration":77,"passed_time":11.08034231,"remaining_time":59.94749303},
{"learn":[0.4665068802],"iteration":78,"passed_time":11.18760764,"remaining_time":59.62003563},
{"learn":[0.4624955082],"iteration":79,"passed_time":11.28165588,"remaining_time":59.22869338},
{"learn":[0.4602290105],"iteration":80,"passed_time":11.3918837,"remaining_time":58.92838603},
{"learn":[0.458038499],"iteration":81,"passed_time":11.49567935,"remaining_time":58.59992645},
{"learn":[0.4549061674],"iteration":82,"passed_time":11.59959777,"remaining_time":58.27749725},
{"learn":[0.4528853747],"iteration":83,"passed_time":11.71810065,"remaining_time":58.03249844},
{"learn":[0.4503386227],"iteration":84,"passed_time":11.82638927,"remaining_time":57.74060645},
{"learn":[0.4482537952],"iteration":85,"passed_time":11.93184409,"remaining_time":57.4393425},
{"learn":[0.4451677568],"iteration":86,"passed_time":12.05510152,"remaining_time":57.22709113},
{"learn":[0.4432873544],"iteration":87,"passed_time":12.17445398,"remaining_time":56.99857998},
{"learn":[0.4396171068],"iteration":88,"passed_time":12.29629904,"remaining_time":56.78403264},
{"learn":[0.4370754065],"iteration":89,"passed_time":12.41603767,"remaining_time":56.56194938},
{"learn":[0.4344509401],"iteration":90,"passed_time":12.55059028,"remaining_time":56.408697},
{"learn":[0.4318630317],"iteration":91,"passed_time":12.68783779,"remaining_time":56.26780236},
{"learn":[0.4288198597],"iteration":92,"passed_time":12.81423814,"remaining_time":56.0795153},
{"learn":[0.4257737724],"iteration":93,"passed_time":12.93435553,"remaining_time":55.86540792},
{"learn":[0.4231174666],"iteration":94,"passed_time":13.06002496,"remaining_time":55.6769485},
{"learn":[0.420213037],"iteration":95,"passed_time":13.17540602,"remaining_time":55.44650033},
{"learn":[0.4176531532],"iteration":96,"passed_time":13.30501755,"remaining_time":55.27754715},
{"learn":[0.4145704397],"iteration":97,"passed_time":13.42761145,"remaining_time":55.08061023},
{"learn":[0.4118146138],"iteration":98,"passed_time":13.54221685,"remaining_time":54.85281774},
{"learn":[0.4098477626],"iteration":99,"passed_time":13.65621325,"remaining_time":54.624853},
{"learn":[0.4073440014],"iteration":100,"passed_time":13.7653505,"remaining_time":54.37994899},
{"learn":[0.4053678024],"iteration":101,"passed_time":13.8683613,"remaining_time":54.11380195},
{"learn":[0.4030768246],"iteration":102,"passed_time":13.98910512,"remaining_time":53.91917215},
{"learn":[0.4019107595],"iteration":103,"passed_time":14.10106456,"remaining_time":53.69251506},
{"learn":[0.3997400349],"iteration":104,"passed_time":14.20359456,"remaining_time":53.43257003},
{"learn":[0.3979333834],"iteration":105,"passed_time":14.31918484,"remaining_time":53.22413987},
{"learn":[0.3958506249],"iteration":106,"passed_time":14.42542323,"remaining_time":52.98309652},
{"learn":[0.3939095312],"iteration":107,"passed_time":14.52480112,"remaining_time":52.7196485},
{"learn":[0.3926987934],"iteration":108,"passed_time":14.63049338,"remaining_time":52.48186157},
{"learn":[0.390583673],"iteration":109,"passed_time":14.7434013,"remaining_time":52.27205915},
{"learn":[0.3882151634],"iteration":110,"passed_time":14.86852552,"remaining_time":52.10681464},
{"learn":[0.38621825],"iteration":111,"passed_time":14.98295137,"remaining_time":51.9052244},
{"learn":[0.3850263229],"iteration":112,"passed_time":15.09168035,"remaining_time":51.68566633},
{"learn":[0.3818553385],"iteration":113,"passed_time":15.19878541,"remaining_time":51.46255412},
{"learn":[0.3800634832],"iteration":114,"passed_time":15.32558113,"remaining_time":51.30738031},
{"learn":[0.3787661],"iteration":115,"passed_time":15.44693913,"remaining_time":51.13469504},
{"learn":[0.3767306543],"iteration":116,"passed_time":15.56113479,"remaining_time":50.93944123},
{"learn":[0.3753282868],"iteration":117,"passed_time":15.65950597,"remaining_time":50.69433289},
{"learn":[0.3736853651],"iteration":118,"passed_time":15.75622014,"remaining_time":50.44638548},
{"learn":[0.3715454549],"iteration":119,"passed_time":15.85466859,"remaining_time":50.20645055},
{"learn":[0.3696070078],"iteration":120,"passed_time":15.95979894,"remaining_time":49.98978345},
{"learn":[0.3684162307],"iteration":121,"passed_time":16.0659216,"remaining_time":49.77801939},
{"learn":[0.3669283008],"iteration":122,"passed_time":16.16486053,"remaining_time":49.54595465},
{"learn":[0.3652355112],"iteration":123,"passed_time":16.26147557,"remaining_time":49.30899043},
{"learn":[0.3637284695],"iteration":124,"passed_time":16.36156677,"remaining_time":49.0847003},
{"learn":[0.3626205347],"iteration":125,"passed_time":16.45468334,"remaining_time":48.84167912},
{"learn":[0.3610182323],"iteration":126,"passed_time":16.55959254,"remaining_time":48.63565369},
{"learn":[0.3594655257],"iteration":127,"passed_time":16.66894818,"remaining_time":48.44413066},
{"learn":[0.3579294758],"iteration":128,"passed_time":16.7795591,"remaining_time":48.25749166},
{"learn":[0.3566877425],"iteration":129,"passed_time":16.88562166,"remaining_time":48.05907702},
{"learn":[0.3549720864],"iteration":130,"passed_time":16.98115188,"remaining_time":47.83240492},
{"learn":[0.3533138807],"iteration":131,"passed_time":17.07984632,"remaining_time":47.61654124},
{"learn":[0.351991231],"iteration":132,"passed_time":17.19307236,"remaining_time":47.44253802},
{"learn":[0.3503417664],"iteration":133,"passed_time":17.29507166,"remaining_time":47.23877781},
{"learn":[0.3486977454],"iteration":134,"passed_time":17.39938864,"remaining_time":47.0427915},
{"learn":[0.3474275702],"iteration":135,"passed_time":17.53955423,"remaining_time":46.94410103},
{"learn":[0.3462315596],"iteration":136,"passed_time":17.6969471,"remaining_time":46.89045108},
{"learn":[0.3449719525],"iteration":137,"passed_time":17.81290951,"remaining_time":46.7266177},
{"learn":[0.3437947912],"iteration":138,"passed_time":17.91972312,"remaining_time":46.53971255},
{"learn":[0.342175978],"iteration":139,"passed_time":18.0235384,"remaining_time":46.34624159},
{"learn":[0.3400730892],"iteration":140,"passed_time":18.13235762,"remaining_time":46.16678288},
{"learn":[0.3392079959],"iteration":141,"passed_time":18.23024726,"remaining_time":45.96076422},
{"learn":[0.3379655737],"iteration":142,"passed_time":18.33273918,"remaining_time":45.76774745},
{"learn":[0.3368428007],"iteration":143,"passed_time":18.43515935,"remaining_time":45.5758106},
{"learn":[0.3353311752],"iteration":144,"passed_time":18.53837618,"remaining_time":45.38705891},
{"learn":[0.3338419497],"iteration":145,"passed_time":18.64189145,"remaining_time":45.20020256},
{"learn":[0.3325144894],"iteration":146,"passed_time":18.74362799,"remaining_time":45.01020871},
{"learn":[0.3308074735],"iteration":147,"passed_time":18.84340005,"remaining_time":44.81673525},
{"learn":[0.3299901552],"iteration":148,"passed_time":18.94311622,"remaining_time":44.62438787},
{"learn":[0.328066755],"iteration":149,"passed_time":19.03383214,"remaining_time":44.41227499},
{"learn":[0.327078758],"iteration":150,"passed_time":19.14534809,"remaining_time":44.24984426},
{"learn":[0.3262829997],"iteration":151,"passed_time":19.24505549,"remaining_time":44.0610481},
{"learn":[0.3245271637],"iteration":152,"passed_time":19.33568679,"remaining_time":43.85283213},
{"learn":[0.3234745824],"iteration":153,"passed_time":19.42258091,"remaining_time":43.63774673},
{"learn":[0.3224197879],"iteration":154,"passed_time":19.50703939,"remaining_time":43.41889412},
{"learn":[0.3208307062],"iteration":155,"passed_time":19.59419498,"remaining_time":43.20771201},
{"learn":[0.3197074904],"iteration":156,"passed_time":19.67910713,"remaining_time":42.99320858},
{"learn":[0.3180452695],"iteration":157,"passed_time":19.77195699,"remaining_time":42.79752716},
{"learn":[0.3171159895],"iteration":158,"passed_time":19.85638679,"remaining_time":42.5850811},
{"learn":[0.3154664216],"iteration":159,"passed_time":19.94203304,"remaining_time":42.37682021},
{"learn":[0.3148144694],"iteration":160,"passed_time":20.03257992,"remaining_time":42.18040121},
{"learn":[0.3131276349],"iteration":161,"passed_time":20.12509477,"remaining_time":41.98939525},
{"learn":[0.3114854948],"iteration":162,"passed_time":20.20965527,"remaining_time":41.78315232},
{"learn":[0.3102230157],"iteration":163,"passed_time":20.29431292,"remaining_time":41.57859232},
{"learn":[0.3082020482],"iteration":164,"passed_time":20.37486677,"remaining_time":41.36715374},
{"learn":[0.3072620477],"iteration":165,"passed_time":20.46533341,"remaining_time":41.1772371},
{"learn":[0.3064027215],"iteration":166,"passed_time":20.58021281,"remaining_time":41.03719081},
{"learn":[0.3055705037],"iteration":167,"passed_time":20.69414584,"remaining_time":40.89557391},
{"learn":[0.3041690632],"iteration":168,"passed_time":20.80991457,"remaining_time":40.75788001},
{"learn":[0.3033599411],"iteration":169,"passed_time":20.90579364,"remaining_time":40.58183472},
{"learn":[0.3022653046],"iteration":170,"passed_time":21.00932223,"remaining_time":40.42144453},
{"learn":[0.3007970823],"iteration":171,"passed_time":21.1036293,"remaining_time":40.24413029},
{"learn":[0.2997242762],"iteration":172,"passed_time":21.19239906,"remaining_time":40.0573092},
{"learn":[0.2984040952],"iteration":173,"passed_time":21.28259776,"remaining_time":39.87429235},
{"learn":[0.2975039973],"iteration":174,"passed_time":21.37797149,"remaining_time":39.70194705},
{"learn":[0.2963193204],"iteration":175,"passed_time":21.47359152,"remaining_time":39.53092985},
{"learn":[0.2952939918],"iteration":176,"passed_time":21.56452732,"remaining_time":39.35221653},
{"learn":[0.2943016836],"iteration":177,"passed_time":21.65909749,"remaining_time":39.18106399},
{"learn":[0.2935025676],"iteration":178,"passed_time":21.76062906,"remaining_time":39.023251},
{"learn":[0.2917891561],"iteration":179,"passed_time":21.84430426,"remaining_time":38.83431868},
{"learn":[0.2905146243],"iteration":180,"passed_time":21.93955435,"remaining_time":38.66694937},
{"learn":[0.2891380916],"iteration":181,"passed_time":22.0334768,"remaining_time":38.49805287},
{"learn":[0.2878959965],"iteration":182,"passed_time":22.12085601,"remaining_time":38.31864129},
{"learn":[0.2869358971],"iteration":183,"passed_time":22.21042909,"remaining_time":38.14399779},
{"learn":[0.2861923842],"iteration":184,"passed_time":22.30364181,"remaining_time":37.97647119},
{"learn":[0.2851892234],"iteration":185,"passed_time":22.39084953,"remaining_time":37.7996062},
{"learn":[0.2843302588],"iteration":186,"passed_time":22.48044302,"remaining_time":37.6276934},
{"learn":[0.2831207094],"iteration":187,"passed_time":22.57953227,"remaining_time":37.47241525},
{"learn":[0.2819550346],"iteration":188,"passed_time":22.67042942,"remaining_time":37.30425159},
{"learn":[0.2811357569],"iteration":189,"passed_time":22.76276146,"remaining_time":37.13924238},
{"learn":[0.2803001003],"iteration":190,"passed_time":22.85553837,"remaining_time":36.97571391},
{"learn":[0.2792586763],"iteration":191,"passed_time":22.94931417,"remaining_time":36.81452481},
{"learn":[0.2781312659],"iteration":192,"passed_time":23.0511917,"remaining_time":36.66692152},
{"learn":[0.2768172186],"iteration":193,"passed_time":23.15400862,"remaining_time":36.52127133},
{"learn":[0.2759532154],"iteration":194,"passed_time":23.24338585,"remaining_time":36.35503941},
{"learn":[0.2743747965],"iteration":195,"passed_time":23.34162813,"remaining_time":36.20334159},
{"learn":[0.2732000642],"iteration":196,"passed_time":23.42803222,"remaining_time":36.03397849},
{"learn":[0.272288291],"iteration":197,"passed_time":23.53051325,"remaining_time":35.88997475},
{"learn":[0.2719345378],"iteration":198,"passed_time":23.63284163,"remaining_time":35.74615743},
{"learn":[0.2711531745],"iteration":199,"passed_time":23.74052461,"remaining_time":35.61078692},
{"learn":[0.2697874226],"iteration":200,"passed_time":23.84595164,"remaining_time":35.47233602},
{"learn":[0.2690061793],"iteration":201,"passed_time":23.94580651,"remaining_time":35.32599178},
{"learn":[0.2679910766],"iteration":202,"passed_time":24.03789711,"remaining_time":35.16874602},
{"learn":[0.2669302209],"iteration":203,"passed_time":24.13909433,"remaining_time":35.02535255},
{"learn":[0.2658224066],"iteration":204,"passed_time":24.2408753,"remaining_time":34.88321079},
{"learn":[0.2650251058],"iteration":205,"passed_time":24.33962037,"remaining_time":34.7371281},
{"learn":[0.2644635531],"iteration":206,"passed_time":24.4370518,"remaining_time":34.58964337},
{"learn":[0.2633973704],"iteration":207,"passed_time":24.53055761,"remaining_time":34.43712896},
{"learn":[0.2622046694],"iteration":208,"passed_time":24.6244941,"remaining_time":34.28577886},
{"learn":[0.2612892732],"iteration":209,"passed_time":24.72310277,"remaining_time":34.14142763},
{"learn":[0.2604090446],"iteration":210,"passed_time":24.8122263,"remaining_time":33.98451849},
{"learn":[0.2596004888],"iteration":211,"passed_time":24.90942353,"remaining_time":33.83921687},
{"learn":[0.2586891327],"iteration":212,"passed_time":24.99637174,"remaining_time":33.68055722},
{"learn":[0.2580419314],"iteration":213,"passed_time":25.08276605,"remaining_time":33.52182752},
{"learn":[0.2575535529],"iteration":214,"passed_time":25.17581969,"remaining_time":33.3725982},
{"learn":[0.2564869876],"iteration":215,"passed_time":25.26768604,"remaining_time":33.22232794},
{"learn":[0.2559803088],"iteration":216,"passed_time":25.35392263,"remaining_time":33.06525394},
{"learn":[0.2555344141],"iteration":217,"passed_time":25.44870474,"remaining_time":32.91988412},
{"learn":[0.2543902331],"iteration":218,"passed_time":25.53933941,"remaining_time":32.76965468},
{"learn":[0.2537011337],"iteration":219,"passed_time":25.6279633,"remaining_time":32.61740784},
{"learn":[0.2531528155],"iteration":220,"passed_time":25.72968199,"remaining_time":32.48226821},
{"learn":[0.2525797583],"iteration":221,"passed_time":25.87356132,"remaining_time":32.40022543},
{"learn":[0.2519054628],"iteration":222,"passed_time":25.99539419,"remaining_time":32.29024301},
{"learn":[0.2514851457],"iteration":223,"passed_time":26.09336678,"remaining_time":32.1507555},
{"learn":[0.2504665673],"iteration":224,"passed_time":26.18792755,"remaining_time":32.007467},
{"learn":[0.2498737928],"iteration":225,"passed_time":26.28010538,"remaining_time":31.86172069},
{"learn":[0.2491182844],"iteration":226,"passed_time":26.37290102,"remaining_time":31.71718933},
{"learn":[0.2482141519],"iteration":227,"passed_time":26.46985191,"remaining_time":31.57806894},
{"learn":[0.2473855064],"iteration":228,"passed_time":26.55776724,"remaining_time":31.42862412},
{"learn":[0.24655355],"iteration":229,"passed_time":26.65030215,"remaining_time":31.28513731},
{"learn":[0.2461922686],"iteration":230,"passed_time":26.75322006,"remaining_time":31.15418267},
{"learn":[0.2456671905],"iteration":231,"passed_time":26.85959969,"remaining_time":31.02746861},
{"learn":[0.2445602257],"iteration":232,"passed_time":26.95782193,"remaining_time":30.89158136},
{"learn":[0.2435846845],"iteration":233,"passed_time":27.04526641,"remaining_time":30.74376438},
{"learn":[0.242828415],"iteration":234,"passed_time":27.13458715,"remaining_time":30.598577},
{"learn":[0.2420189152],"iteration":235,"passed_time":27.22259635,"remaining_time":30.45239592},
{"learn":[0.2412934996],"iteration":236,"passed_time":27.32815682,"remaining_time":30.32618246},
{"learn":[0.2405294594],"iteration":237,"passed_time":27.41646525,"remaining_time":30.18115082},
{"learn":[0.2396774287],"iteration":238,"passed_time":27.50714436,"remaining_time":30.03918276},
{"learn":[0.2389735518],"iteration":239,"passed_time":27.59570097,"remaining_time":29.89534272},
{"learn":[0.2376419883],"iteration":240,"passed_time":27.68503761,"remaining_time":29.75279976},
{"learn":[0.2367625601],"iteration":241,"passed_time":27.77638269,"remaining_time":29.61283774},
{"learn":[0.2362830316],"iteration":242,"passed_time":27.86912429,"remaining_time":29.47475285},
{"learn":[0.2356965949],"iteration":243,"passed_time":27.96712272,"remaining_time":29.34255498},
{"learn":[0.235257027],"iteration":244,"passed_time":28.06428541,"remaining_time":29.20976645},
{"learn":[0.2345781651],"iteration":245,"passed_time":28.1521027,"remaining_time":29.06761823},
{"learn":[0.2343146706],"iteration":246,"passed_time":28.23832248,"remaining_time":28.92427364},
{"learn":[0.2340293138],"iteration":247,"passed_time":28.33363575,"remaining_time":28.79062987},
{"learn":[0.233143065],"iteration":248,"passed_time":28.42724219,"remaining_time":28.65557345},
{"learn":[0.2321589689],"iteration":249,"passed_time":28.52557995,"remaining_time":28.52557995},
{"learn":[0.2317194289],"iteration":250,"passed_time":28.62773099,"remaining_time":28.39962158},
{"learn":[0.2307908711],"iteration":251,"passed_time":28.73613297,"remaining_time":28.28000387},
{"learn":[0.2302933465],"iteration":252,"passed_time":28.8399207,"remaining_time":28.15597001},
{"learn":[0.2293937928],"iteration":253,"passed_time":28.94633893,"remaining_time":28.03464321},
{"learn":[0.2288607314],"iteration":254,"passed_time":29.04400079,"remaining_time":27.90502037},
{"learn":[0.2285682189],"iteration":255,"passed_time":29.14611653,"remaining_time":27.77989232},
{"learn":[0.2278149899],"iteration":256,"passed_time":29.25578521,"remaining_time":27.66208484},
{"learn":[0.2271174906],"iteration":257,"passed_time":29.35453343,"remaining_time":27.53409725},
{"learn":[0.2267358166],"iteration":258,"passed_time":29.45988085,"remaining_time":27.412476},
{"learn":[0.2261074287],"iteration":259,"passed_time":29.55842632,"remaining_time":27.28470122},
{"learn":[0.2255956304],"iteration":260,"passed_time":29.65797294,"remaining_time":27.15806717},
{"learn":[0.2248116775],"iteration":261,"passed_time":29.75093517,"remaining_time":27.02565867},
{"learn":[0.2241681081],"iteration":262,"passed_time":29.84145795,"remaining_time":26.89135184},
{"learn":[0.223393731],"iteration":263,"passed_time":29.93357958,"remaining_time":26.75880599},
{"learn":[0.2226717391],"iteration":264,"passed_time":30.02316408,"remaining_time":26.62431532},
{"learn":[0.2221508445],"iteration":265,"passed_time":30.11021196,"remaining_time":26.48793082},
{"learn":[0.2218400734],"iteration":266,"passed_time":30.20125812,"remaining_time":26.35540503},
{"learn":[0.2212014987],"iteration":267,"passed_time":30.28375178,"remaining_time":26.21578512},
{"learn":[0.220627298],"iteration":268,"passed_time":30.36848708,"remaining_time":26.07851493},
{"learn":[0.2198981429],"iteration":269,"passed_time":30.45448458,"remaining_time":25.94270909},
{"learn":[0.2195169694],"iteration":270,"passed_time":30.54463102,"remaining_time":25.81077676},
{"learn":[0.218944127],"iteration":271,"passed_time":30.63077124,"remaining_time":25.67579354},
{"learn":[0.2186308331],"iteration":272,"passed_time":30.7300204,"remaining_time":25.55206825},
{"learn":[0.2181694308],"iteration":273,"passed_time":30.81575662,"remaining_time":25.4173759},
{"learn":[0.2174718357],"iteration":274,"passed_time":30.90193889,"remaining_time":25.28340454},
{"learn":[0.2169813108],"iteration":275,"passed_time":30.99536102,"remaining_time":25.15565532},
{"learn":[0.2164603828],"iteration":276,"passed_time":31.08282159,"remaining_time":25.02335456},
{"learn":[0.2159783143],"iteration":277,"passed_time":31.16829375,"remaining_time":24.88978854},
{"learn":[0.2154535761],"iteration":278,"passed_time":31.25458896,"remaining_time":24.75721922},
{"learn":[0.214535779],"iteration":279,"passed_time":31.34120409,"remaining_time":24.62523179},
{"learn":[0.2138384337],"iteration":280,"passed_time":31.42766219,"remaining_time":24.49344491},
{"learn":[0.2132499455],"iteration":281,"passed_time":31.51371039,"remaining_time":24.36166264},
{"learn":[0.2127531929],"iteration":282,"passed_time":31.59750821,"remaining_time":24.22847803},
{"learn":[0.2123042456],"iteration":283,"passed_time":31.68964146,"remaining_time":24.10198083},
{"learn":[0.2115960657],"iteration":284,"passed_time":31.78977421,"remaining_time":23.98175949},
{"learn":[0.2110264167],"iteration":285,"passed_time":31.88544391,"remaining_time":23.85833915},
{"learn":[0.210468147],"iteration":286,"passed_time":31.97526799,"remaining_time":23.7307738},
{"learn":[0.2101558124],"iteration":287,"passed_time":32.06601095,"remaining_time":23.60414695},
{"learn":[0.2093336966],"iteration":288,"passed_time":32.1559229,"remaining_time":23.4771617},
{"learn":[0.2090753287],"iteration":289,"passed_time":32.2514526,"remaining_time":23.35450016},
{"learn":[0.2086279455],"iteration":290,"passed_time":32.33561711,"remaining_time":23.22386246},
{"learn":[0.208352543],"iteration":291,"passed_time":32.41704372,"remaining_time":23.09159279},
{"learn":[0.2080008038],"iteration":292,"passed_time":32.50805053,"remaining_time":22.96643843},
{"learn":[0.2074584268],"iteration":293,"passed_time":32.59486607,"remaining_time":22.83857963},
{"learn":[0.2068786153],"iteration":294,"passed_time":32.69056605,"remaining_time":22.71717302},
{"learn":[0.2065441761],"iteration":295,"passed_time":32.79131683,"remaining_time":22.59942106},
{"learn":[0.2056206439],"iteration":296,"passed_time":32.88588448,"remaining_time":22.4775574},
{"learn":[0.2053272995],"iteration":297,"passed_time":32.9733229,"remaining_time":22.35104438},
{"learn":[0.2047951327],"iteration":298,"passed_time":33.06061214,"remaining_time":22.22469244},
{"learn":[0.2043497003],"iteration":299,"passed_time":33.15336312,"remaining_time":22.10224208},
{"learn":[0.2038721687],"iteration":300,"passed_time":33.23582286,"remaining_time":21.97318522},
{"learn":[0.2034114904],"iteration":301,"passed_time":33.32429623,"remaining_time":21.84837965},
{"learn":[0.2032393156],"iteration":302,"passed_time":33.40870451,"remaining_time":21.72117092},
{"learn":[0.2026696702],"iteration":303,"passed_time":33.49132948,"remaining_time":21.59309401},
{"learn":[0.2024511657],"iteration":304,"passed_time":33.58245856,"remaining_time":21.4707522},
{"learn":[0.2018830047],"iteration":305,"passed_time":33.66953888,"remaining_time":21.34604752},
{"learn":[0.2011632074],"iteration":306,"passed_time":33.75735954,"remaining_time":21.22205339},
{"learn":[0.200757466],"iteration":307,"passed_time":33.85450475,"remaining_time":21.10410686},
{"learn":[0.2001504974],"iteration":308,"passed_time":33.94523565,"remaining_time":20.98233013},
{"learn":[0.1995519995],"iteration":309,"passed_time":34.03207888,"remaining_time":20.85837092},
{"learn":[0.1991074983],"iteration":310,"passed_time":34.11243793,"remaining_time":20.73070987},
{"learn":[0.1982750972],"iteration":311,"passed_time":34.202712,"remaining_time":20.60932646},
{"learn":[0.1976608203],"iteration":312,"passed_time":34.29078023,"remaining_time":20.48682397},
{"learn":[0.1974169266],"iteration":313,"passed_time":34.3723694,"remaining_time":20.36070289},
{"learn":[0.1970610072],"iteration":314,"passed_time":34.45978013,"remaining_time":20.23828357},
{"learn":[0.1966956578],"iteration":315,"passed_time":34.54344317,"remaining_time":20.11390362},
{"learn":[0.1962955298],"iteration":316,"passed_time":34.64697399,"remaining_time":20.00124997},
{"learn":[0.1958884311],"iteration":317,"passed_time":34.79336127,"remaining_time":19.91318161},
{"learn":[0.1954681388],"iteration":318,"passed_time":34.88340427,"remaining_time":19.79277797},
{"learn":[0.1950809866],"iteration":319,"passed_time":34.96698379,"remaining_time":19.66892838},
{"learn":[0.1946894239],"iteration":320,"passed_time":35.06627781,"remaining_time":19.55409261},
{"learn":[0.1942784792],"iteration":321,"passed_time":35.15686353,"remaining_time":19.43453947},
{"learn":[0.1938675752],"iteration":322,"passed_time":35.24584595,"remaining_time":19.3142871},
{"learn":[0.1931228027],"iteration":323,"passed_time":35.33678603,"remaining_time":19.19529118},
{"learn":[0.192753291],"iteration":324,"passed_time":35.42172073,"remaining_time":19.07323424},
{"learn":[0.1923626181],"iteration":325,"passed_time":35.5056373,"remaining_time":18.95086162},
{"learn":[0.1920297397],"iteration":326,"passed_time":35.58976029,"remaining_time":18.82883343},
{"learn":[0.1915441102],"iteration":327,"passed_time":35.68727672,"remaining_time":18.71405975},
{"learn":[0.1911942266],"iteration":328,"passed_time":35.77464901,"remaining_time":18.59411848},
{"learn":[0.1907664242],"iteration":329,"passed_time":35.85883022,"remaining_time":18.47273072},
{"learn":[0.1902503933],"iteration":330,"passed_time":35.93927162,"remaining_time":18.34965832},
{"learn":[0.1897471691],"iteration":331,"passed_time":36.01899226,"remaining_time":18.22647801},
{"learn":[0.189297448],"iteration":332,"passed_time":36.1026835,"remaining_time":18.10554998},
{"learn":[0.1887066079],"iteration":333,"passed_time":36.18325195,"remaining_time":17.98329288},
{"learn":[0.1885053625],"iteration":334,"passed_time":36.26407808,"remaining_time":17.86141159},
{"learn":[0.1882553427],"iteration":335,"passed_time":36.34551455,"remaining_time":17.74007258},
{"learn":[0.1878762125],"iteration":336,"passed_time":36.43386507,"remaining_time":17.62231456},
{"learn":[0.1875587856],"iteration":337,"passed_time":36.52478161,"remaining_time":17.50596042},
{"learn":[0.1872990277],"iteration":338,"passed_time":36.61217225,"remaining_time":17.3880818},
{"learn":[0.1868824188],"iteration":339,"passed_time":36.71162039,"remaining_time":17.27605666},
{"learn":[0.1866269407],"iteration":340,"passed_time":36.80505486,"remaining_time":17.16130124},
{"learn":[0.1864465205],"iteration":341,"passed_time":36.90129353,"remaining_time":17.04796602},
{"learn":[0.1858962738],"iteration":342,"passed_time":36.99096208,"remaining_time":16.93172317},
{"learn":[0.1855100496],"iteration":343,"passed_time":37.09037548,"remaining_time":16.82005399},
{"learn":[0.1851960707],"iteration":344,"passed_time":37.18419848,"remaining_time":16.70594424},
{"learn":[0.1848314989],"iteration":345,"passed_time":37.27091114,"remaining_time":16.58878704},
{"learn":[0.1845195725],"iteration":346,"passed_time":37.3599586,"remaining_time":16.47283477},
{"learn":[0.1841115212],"iteration":347,"passed_time":37.45380202,"remaining_time":16.35913192},
{"learn":[0.1838170713],"iteration":348,"passed_time":37.54485758,"remaining_time":16.24433666},
{"learn":[0.1836845521],"iteration":349,"passed_time":37.63504187,"remaining_time":16.12930366},
{"learn":[0.1833742333],"iteration":350,"passed_time":37.73520331,"remaining_time":16.01864756},
{"learn":[0.1828973898],"iteration":351,"passed_time":37.84394665,"remaining_time":15.91165939},
{"learn":[0.182363661],"iteration":352,"passed_time":37.95038306,"remaining_time":15.8037006},
{"learn":[0.1819281601],"iteration":353,"passed_time":38.05042423,"remaining_time":15.69311282},
{"learn":[0.181747571],"iteration":354,"passed_time":38.16180422,"remaining_time":15.58721581},
{"learn":[0.1815083454],"iteration":355,"passed_time":38.25349714,"remaining_time":15.47332469},
{"learn":[0.1811208683],"iteration":356,"passed_time":38.34659272,"remaining_time":15.36011977},
{"learn":[0.1808406721],"iteration":357,"passed_time":38.43342997,"remaining_time":15.24454485},
{"learn":[0.1804539458],"iteration":358,"passed_time":38.51807485,"remaining_time":15.12826895},
{"learn":[0.1801598118],"iteration":359,"passed_time":38.61989522,"remaining_time":15.01884814},
{"learn":[0.1797843084],"iteration":360,"passed_time":38.71413559,"remaining_time":14.90655082},
{"learn":[0.1794605569],"iteration":361,"passed_time":38.79973978,"remaining_time":14.79106102},
{"learn":[0.178919259],"iteration":362,"passed_time":38.89286384,"remaining_time":14.67857395},
{"learn":[0.1786782114],"iteration":363,"passed_time":38.99078388,"remaining_time":14.56798518},
{"learn":[0.1783956683],"iteration":364,"passed_time":39.07795416,"remaining_time":14.45348989},
{"learn":[0.1781608942],"iteration":365,"passed_time":39.16070729,"remaining_time":14.33752671},
{"learn":[0.1778376897],"iteration":366,"passed_time":39.25465829,"remaining_time":14.22580259},
{"learn":[0.1773979608],"iteration":367,"passed_time":39.34345072,"remaining_time":14.11232472},
{"learn":[0.1770942273],"iteration":368,"passed_time":39.43662653,"remaining_time":14.00053679},
{"learn":[0.1766809154],"iteration":369,"passed_time":39.53104871,"remaining_time":13.88928739},
{"learn":[0.1763364831],"iteration":370,"passed_time":39.62308501,"remaining_time":13.7772991},
{"learn":[0.1761381289],"iteration":371,"passed_time":39.7145472,"remaining_time":13.66522054},
{"learn":[0.1758762207],"iteration":372,"passed_time":39.81701364,"remaining_time":13.55699928},
{"learn":[0.1756219041],"iteration":373,"passed_time":39.91870298,"remaining_time":13.44854699},
{"learn":[0.17530755],"iteration":374,"passed_time":40.01199808,"remaining_time":13.33733269},
{"learn":[0.1748910788],"iteration":375,"passed_time":40.11319079,"remaining_time":13.22881824},
{"learn":[0.1745144411],"iteration":376,"passed_time":40.20538069,"remaining_time":13.11740537},
{"learn":[0.174208516],"iteration":377,"passed_time":40.29232753,"remaining_time":13.00440201},
{"learn":[0.1738246316],"iteration":378,"passed_time":40.38497409,"remaining_time":12.89335584},
{"learn":[0.1735420661],"iteration":379,"passed_time":40.47571605,"remaining_time":12.78180507},
{"learn":[0.1733233659],"iteration":380,"passed_time":40.56630516,"remaining_time":12.67031579},
{"learn":[0.173066341],"iteration":381,"passed_time":40.6539549,"remaining_time":12.55802795},
{"learn":[0.1728933747],"iteration":382,"passed_time":40.73618851,"remaining_time":12.44421425},
{"learn":[0.1725024938],"iteration":383,"passed_time":40.81890476,"remaining_time":12.33071081},
{"learn":[0.1721266635],"iteration":384,"passed_time":40.90527043,"remaining_time":12.2184574},
{"learn":[0.171809085],"iteration":385,"passed_time":40.98426237,"remaining_time":12.10416039},
{"learn":[0.171521324],"iteration":386,"passed_time":41.06978544,"remaining_time":11.99195285},
{"learn":[0.1711761834],"iteration":387,"passed_time":41.14780381,"remaining_time":11.87771656},
{"learn":[0.170999119],"iteration":388,"passed_time":41.22629982,"remaining_time":11.76380278},
{"learn":[0.1708249227],"iteration":389,"passed_time":41.30824868,"remaining_time":11.6510445},
{"learn":[0.1704980759],"iteration":390,"passed_time":41.38961308,"remaining_time":11.53828088},
{"learn":[0.1702497798],"iteration":391,"passed_time":41.46321638,"remaining_time":11.42353921},
{"learn":[0.1699073937],"iteration":392,"passed_time":41.54323362,"remaining_time":11.31075317},
{"learn":[0.1696540709],"iteration":393,"passed_time":41.6255081,"remaining_time":11.19874076},
{"learn":[0.1694363895],"iteration":394,"passed_time":41.7057488,"remaining_time":11.08633829},
{"learn":[0.1690877332],"iteration":395,"passed_time":41.79044462,"remaining_time":10.97526828},
{"learn":[0.1688680619],"iteration":396,"passed_time":41.86768895,"remaining_time":10.86239789},
{"learn":[0.168489239],"iteration":397,"passed_time":41.94706446,"remaining_time":10.7502527},
{"learn":[0.1682121928],"iteration":398,"passed_time":42.02920003,"remaining_time":10.63897043},
{"learn":[0.1679319512],"iteration":399,"passed_time":42.11019163,"remaining_time":10.52754791},
{"learn":[0.1675334426],"iteration":400,"passed_time":42.19038156,"remaining_time":10.41607924},
{"learn":[0.1672364677],"iteration":401,"passed_time":42.28214353,"remaining_time":10.30758723},
{"learn":[0.1670088907],"iteration":402,"passed_time":42.37688301,"remaining_time":10.19989492},
{"learn":[0.1666911659],"iteration":403,"passed_time":42.46715695,"remaining_time":10.09120561},
{"learn":[0.166326424],"iteration":404,"passed_time":42.57067915,"remaining_time":9.985714861},
{"learn":[0.165945914],"iteration":405,"passed_time":42.66707211,"remaining_time":9.878583198},
{"learn":[0.1656981167],"iteration":406,"passed_time":42.76838212,"remaining_time":9.772627854},
{"learn":[0.1653509492],"iteration":407,"passed_time":42.86252781,"remaining_time":9.665079801},
{"learn":[0.1650792714],"iteration":408,"passed_time":42.95776985,"remaining_time":9.557841213},
{"learn":[0.1648775506],"iteration":409,"passed_time":43.04742627,"remaining_time":9.449435034},
{"learn":[0.1645621573],"iteration":410,"passed_time":43.14266593,"remaining_time":9.342329119},
{"learn":[0.1644092051],"iteration":411,"passed_time":43.22998055,"remaining_time":9.233588078},
{"learn":[0.1641899063],"iteration":412,"passed_time":43.3165789,"remaining_time":9.124799913},
{"learn":[0.1640465806],"iteration":413,"passed_time":43.40820547,"remaining_time":9.017163455},
{"learn":[0.1638767838],"iteration":414,"passed_time":43.50585966,"remaining_time":8.910838725},
{"learn":[0.1636932505],"iteration":415,"passed_time":43.59456799,"remaining_time":8.802749306},
{"learn":[0.1634911909],"iteration":416,"passed_time":43.68842249,"remaining_time":8.695777137},
{"learn":[0.1631553993],"iteration":417,"passed_time":43.78392724,"remaining_time":8.589191468},
{"learn":[0.1628697395],"iteration":418,"passed_time":43.87402931,"remaining_time":8.481614257},
{"learn":[0.1625704063],"iteration":419,"passed_time":43.96401836,"remaining_time":8.374098735},
{"learn":[0.1621612561],"iteration":420,"passed_time":44.06002606,"remaining_time":8.267795865},
{"learn":[0.161863779],"iteration":421,"passed_time":44.15414282,"remaining_time":8.161192275},
{"learn":[0.1615848476],"iteration":422,"passed_time":44.24333916,"remaining_time":8.053752046},
{"learn":[0.1613437796],"iteration":423,"passed_time":44.33748321,"remaining_time":7.947284727},
{"learn":[0.1611894683],"iteration":424,"passed_time":44.43044156,"remaining_time":7.840666158},
{"learn":[0.1608957283],"iteration":425,"passed_time":44.517026,"remaining_time":7.733004517},
{"learn":[0.1606327484],"iteration":426,"passed_time":44.61573908,"remaining_time":7.627515112},
{"learn":[0.160396182],"iteration":427,"passed_time":44.70360857,"remaining_time":7.520233217},
{"learn":[0.1601634724],"iteration":428,"passed_time":44.79266116,"remaining_time":7.413237628},
{"learn":[0.1597258938],"iteration":429,"passed_time":44.88330209,"remaining_time":7.306584061},
{"learn":[0.1594757425],"iteration":430,"passed_time":44.98041877,"remaining_time":7.201041521},
{"learn":[0.1591789977],"iteration":431,"passed_time":45.069838,"remaining_time":7.094326351},
{"learn":[0.1588379811],"iteration":432,"passed_time":45.15998487,"remaining_time":6.987803663},
{"learn":[0.1586764389],"iteration":433,"passed_time":45.24783969,"remaining_time":6.881007878},
{"learn":[0.1585185611],"iteration":434,"passed_time":45.32833295,"remaining_time":6.773199176},
{"learn":[0.158355733],"iteration":435,"passed_time":45.4132287,"remaining_time":6.666162011},
{"learn":[0.1580723192],"iteration":436,"passed_time":45.49708258,"remaining_time":6.559075979},
{"learn":[0.1577522544],"iteration":437,"passed_time":45.58202437,"remaining_time":6.452250026},
{"learn":[0.1575773459],"iteration":438,"passed_time":45.67498748,"remaining_time":6.346638351},
{"learn":[0.1572824984],"iteration":439,"passed_time":45.75999596,"remaining_time":6.239999449},
{"learn":[0.1569430515],"iteration":440,"passed_time":45.84429676,"remaining_time":6.133363966},
{"learn":[0.1566053649],"iteration":441,"passed_time":45.92786159,"remaining_time":6.026732969},
{"learn":[0.1563868322],"iteration":442,"passed_time":46.01501561,"remaining_time":5.920667923},
{"learn":[0.1561268654],"iteration":443,"passed_time":46.10606816,"remaining_time":5.815179768},
{"learn":[0.1557395041],"iteration":444,"passed_time":46.19233763,"remaining_time":5.709165325},
{"learn":[0.1555003599],"iteration":445,"passed_time":46.27739599,"remaining_time":5.603092788},
{"learn":[0.1552922287],"iteration":446,"passed_time":46.36184044,"remaining_time":5.497041483},
{"learn":[0.1551030719],"iteration":447,"passed_time":46.44849854,"remaining_time":5.39134358},
{"learn":[0.1548845378],"iteration":448,"passed_time":46.53019107,"remaining_time":5.285166469},
{"learn":[0.1546692411],"iteration":449,"passed_time":46.60771843,"remaining_time":5.178635381},
{"learn":[0.1542695653],"iteration":450,"passed_time":46.69682624,"remaining_time":5.073491099},
{"learn":[0.1539826774],"iteration":451,"passed_time":46.78016543,"remaining_time":4.967805178},
{"learn":[0.1537456626],"iteration":452,"passed_time":46.86338045,"remaining_time":4.862205036},
{"learn":[0.1535073879],"iteration":453,"passed_time":46.94052042,"remaining_time":4.756087972},
{"learn":[0.153238285],"iteration":454,"passed_time":47.02008539,"remaining_time":4.650338115},
{"learn":[0.1529618216],"iteration":455,"passed_time":47.10879695,"remaining_time":4.545585671},
{"learn":[0.1527692994],"iteration":456,"passed_time":47.20447297,"remaining_time":4.441558726},
{"learn":[0.1524455156],"iteration":457,"passed_time":47.29136618,"remaining_time":4.336762838},
{"learn":[0.1522722492],"iteration":458,"passed_time":47.38722613,"remaining_time":4.232845907},
{"learn":[0.1519990454],"iteration":459,"passed_time":47.48238258,"remaining_time":4.128902833},
{"learn":[0.1518314506],"iteration":460,"passed_time":47.5799104,"remaining_time":4.025198494},
{"learn":[0.151611024],"iteration":461,"passed_time":47.67293629,"remaining_time":3.921150604},
{"learn":[0.1513806732],"iteration":462,"passed_time":47.76830472,"remaining_time":3.817337526},
{"learn":[0.1511671603],"iteration":463,"passed_time":47.85308628,"remaining_time":3.712739453},
{"learn":[0.1509530867],"iteration":464,"passed_time":47.94218974,"remaining_time":3.608551916},
{"learn":[0.1507405524],"iteration":465,"passed_time":48.02718748,"remaining_time":3.504129558},
{"learn":[0.1505361006],"iteration":466,"passed_time":48.11474833,"remaining_time":3.399971509},
{"learn":[0.1502680083],"iteration":467,"passed_time":48.19939011,"remaining_time":3.295684794},
{"learn":[0.1500428293],"iteration":468,"passed_time":48.28378067,"remaining_time":3.191465247},
{"learn":[0.1497799725],"iteration":469,"passed_time":48.3829351,"remaining_time":3.088272453},
{"learn":[0.1495874852],"iteration":470,"passed_time":48.49126728,"remaining_time":2.985661892},
{"learn":[0.1492998013],"iteration":471,"passed_time":48.60310602,"remaining_time":2.883235103},
{"learn":[0.149014665],"iteration":472,"passed_time":48.72487711,"remaining_time":2.78133548},
{"learn":[0.1488573971],"iteration":473,"passed_time":48.83090808,"remaining_time":2.678488629},
{"learn":[0.1487053627],"iteration":474,"passed_time":48.91915251,"remaining_time":2.574692237},
{"learn":[0.1484723162],"iteration":475,"passed_time":49.00933605,"remaining_time":2.47105896},
{"learn":[0.1483571971],"iteration":476,"passed_time":49.09575069,"remaining_time":2.367300348},
{"learn":[0.148228935],"iteration":477,"passed_time":49.18933462,"remaining_time":2.263944271},
{"learn":[0.1478475824],"iteration":478,"passed_time":49.27592499,"remaining_time":2.16032239},
{"learn":[0.1476220845],"iteration":479,"passed_time":49.36476992,"remaining_time":2.056865413},
{"learn":[0.1474725175],"iteration":480,"passed_time":49.4503239,"remaining_time":1.953339198},
{"learn":[0.1472465875],"iteration":481,"passed_time":49.54036076,"remaining_time":1.850054966},
{"learn":[0.147087146],"iteration":482,"passed_time":49.62629557,"remaining_time":1.746681211},
{"learn":[0.146896473],"iteration":483,"passed_time":49.70979457,"remaining_time":1.643298994},
{"learn":[0.1467646702],"iteration":484,"passed_time":49.80414331,"remaining_time":1.540334329},
{"learn":[0.146563638],"iteration":485,"passed_time":49.89597244,"remaining_time":1.437332539},
{"learn":[0.1462846313],"iteration":486,"passed_time":49.98781606,"remaining_time":1.33437702},
{"learn":[0.1460031259],"iteration":487,"passed_time":50.08737002,"remaining_time":1.23165664},
{"learn":[0.1457541852],"iteration":488,"passed_time":50.18511826,"remaining_time":1.128908591},
{"learn":[0.145604195],"iteration":489,"passed_time":50.28637929,"remaining_time":1.026252639},
{"learn":[0.1454740108],"iteration":490,"passed_time":50.38255378,"remaining_time":0.9235091325},
{"learn":[0.145313609],"iteration":491,"passed_time":50.48375451,"remaining_time":0.8208740571},
{"learn":[0.14503697],"iteration":492,"passed_time":50.57706755,"remaining_time":0.718132805},
{"learn":[0.1448662468],"iteration":493,"passed_time":50.68268472,"remaining_time":0.6155791666},
{"learn":[0.14454031],"iteration":494,"passed_time":50.7731455,"remaining_time":0.5128600556},
{"learn":[0.1443258675],"iteration":495,"passed_time":50.86604873,"remaining_time":0.4102100704},
{"learn":[0.1441993874],"iteration":496,"passed_time":50.95651966,"remaining_time":0.3075846257},
{"learn":[0.1440945578],"iteration":497,"passed_time":51.05585133,"remaining_time":0.2050435796},
{"learn":[0.1438978521],"iteration":498,"passed_time":51.13909035,"remaining_time":0.102483147},
{"learn":[0.1437652856],"iteration":499,"passed_time":51.22134721,"remaining_time":0}
]}